setup.cfg
setup.py
scs_sdk.egg-info/PKG-INFO
scs_sdk.egg-info/SOURCES.txt
scs_sdk.egg-info/dependency_links.txt
scs_sdk.egg-info/requires.txt
scs_sdk.egg-info/top_level.txt
sinastorage/__init__.py
sinastorage/bucket.py
sinastorage/multipart.py
sinastorage/streaming.py
sinastorage/utils.py