Metadata-Version: 1.1
Name: scs-sdk
Version: 1.1.0
Summary: Python SDK For 新浪云存储
Home-page: http://open.sinastorage.com/
Author: sina cloud storage
Author-email: hanchao3@staff.sina.com.cn
License: BSD
Download-URL: https://github.com/SinaCloudStorage/SinaStorage-SDK-Python
Keywords: sina,scs,sinacloudstorage
Platform: UNKNOWN
Classifier: Development Status :: 3 - Alpha
Classifier: Intended Audience :: Developers
Classifier: Topic :: Software Development :: Build Tools
Classifier: License :: OSI Approved :: MIT License
Classifier: Programming Language :: Python :: 2.7
